traktor_client/__init__.py
traktor_client/__main__.py
traktor_client/client.py
traktor_client/config.py
traktor_client/models.py
traktor_client/version.py
traktor_client/commands/__init__.py
traktor_client/commands/app.py
traktor_client/commands/client.py
traktor_client-0.0.5.dist-info/AUTHORS
traktor_client-0.0.5.dist-info/LICENSE
traktor_client-0.0.5.dist-info/METADATA
traktor_client-0.0.5.dist-info/WHEEL
traktor_client-0.0.5.dist-info/entry_points.txt
traktor_client-0.0.5.dist-info/top_level.txt
traktor_client-0.0.5.dist-info/RECORD
